{
  "posts": [
    {
      "id": "1",
      "title": "a title",
      "views": 100
    },
    {
      "id": "2",
      "title": "another title",
      "views": 200
    }
  ],
  "comments": [
    {
      "id": "1",
      "text": "a comment about post 1",
      "postId": "1"
    },
    {
      "id": "2",
      "text": "another comment about post 1",
      "postId": "1"
    }
  ],
  "profile": {
    "name": "typicode"
  },
  "employees": [
    {
      "firstName": "Rahul",
      "lastName": "Sharmaaa",
      "email": "dharmenderkumar223@gmail.com",
      "dob": "1995-07-24T18:30:00.000Z",
      "gender": "male",
      "education": "Graduate",
      "company": "Infinity Soft Systems",
      "experience": 2,
      "package": 4,
      "id": "c884"
    },
    {
      "id": "3bb7",
      "firstName": "Dharmender",
      "lastName": "Verma",
      "email": "imdharmenderverma@gmail.com",
      "dob": "1996-07-24T18:30:00.000Z",
      "gender": "male",
      "education": "Post Graduate",
      "company": "Google",
      "experience": 3,
      "package": 12
    }
  ]
}